{"label": "bag", "p": 8.067768794717267e-05, "predictions": ["cube", "cubicle", "stand", "tote", "parcel", "bundle", "discard", "bin", "file", "box", "unlock", "receptacle", "carton", "gap", "staple", "podium", "pack", "recycle", "siphon", "fired", "securely", "breadth", "padlock", "node", "bypass", "fix", "folder", "product", "gave", "plus", "customize", "one", "ton", "mover", "ideal", "bending", "hamper", "carrying", "packaging", "nuance", "donated", "decoy", "lit", "wholesale", "lavatory", "with", "liter", "paperboard", "net", "cornerstone", "android", "email", "protect", "rectangular", "in", "remind", "pressing", "attached", "counter", "twelve", "if", "toolkit", "safekeeping", "label", "instead", "fill", "garbage", "wit", "noted", "instant", "note", "finale", "upturn", "straw", "quip", "unify", "storage", "confinement", "copied", "redeemer", "combination", "myself", "furnace", "impossible", "resubmit", "booth", "wreath", "gift", "flip", "stack", "hierarchy", "load", "attachment", "constancy", "suitcase", "weight", "mudguard", "erect", "genus", "present"]}
{"label": "bag", "p": 0.4025755226612091, "predictions": ["bag", "handbag", "purse", "princely", "suitcase", "luggage", "tote", "briefcase", "expandable", "toolkit", "gallantry", "beg", "backpack", "waxed", "pack", "pouch", "drawstring", "allocate", "reparation", "built", "label", "bagful", "traveling", "hanging", "prevail", "commander", "wheeled", "embark", "wagon", "porter", "slightness", "belongings", "travel", "promotional", "stirrup", "fluster", "baggage", "saintly", "valuables", "directly", "pepper", "ethnic", "vacuum", "importation", "outwards", "excess", "hardily", "goods", "bypass", "woolly", "beeswax", "ton", "kit", "weight", "erect", "bargain", "conceal", "significance", "solicitation", "radio", "bonded", "collective", "lumberman", "obesity", "acorn", "bundle", "weighty", "frequent", "satire", "carbohydrate", "delightful", "beneficiary", "moistness", "deluxe", "cap", "withheld", "limp", "gong", "regulation", "backside", "parcel", "noted", "discount", "baseball", "cheerfully", "prognosis", "wire", "grew", "inadvertently", "acknowledge", "diet", "registration", "bushiness", "omit", "considered", "inhabitant", "adventurously", "abolish", "transpire", "indicative"]}
{"label": "bag", "p": 0.7083356380462646, "predictions": ["bag", "handbag", "briefcase", "gallantry", "suitcase", "princely", "label", "purse", "toolkit", "cot", "expandable", "backpack", "transpire", "wagon", "outwards", "tote", "drawstring", "pack", "luggage", "watertight", "waxed", "covert", "collapsible", "trolley", "fluster", "beg", "wheeled", "pouch", "reversible", "allocate", "kit", "built", "conceal", "porter", "northwards", "importation", "saintly", "armband", "desirably", "responder", "biz", "wallet", "tether", "bagful", "mover", "pedigree", "harness", "belted", "parcel", "strap", "peasant", "acknowledge", "booster", "prevail", "stint", "siphon", "retrospectively", "sometime", "today", "halter", "medic", "duskiness", "credential", "bundle", "baggage", "carry", "splendor", "instep", "condition", "apron", "craftsman", "banner", "confidentiality", "worming", "zip", "deluxe", "valuables", "quiver", "beneficiary", "reviewer", "collar", "termination", "incompleteness", "folder", "pocket", "net", "mouth", "commander", "hospitalization", "scholarly", "backrest", "aid", "fraud", "survival", "shorts", "in", "gift", "separation", "acceleration", "inhabitant"]}
{"label": "bag", "p": 0.21123073995113373, "predictions": ["bag", "label", "built", "purse", "suitcase", "handbag", "bargain", "prevail", "opening", "cot", "wallet", "responder", "pin", "tag", "toolkit", "northwards", "pocket", "unlock", "reversible", "allocate", "peeler", "python", "deal", "sticker", "princely", "rapport", "lumberman", "banner", "carry", "harness", "like", "stirrup", "zip", "sandal", "subtraction", "file", "erect", "taxi", "pack", "calendar", "hardened", "copied", "armband", "disk", "credential", "tote", "knit", "sport", "woolen", "boomerang", "reparation", "vascular", "look", "ethnic", "prognosis", "bottom", "schoolbook", "save", "flask", "topic", "peer", "lots", "expensive", "today", "beg", "availability", "luggage", "orderly", "drawstring", "richly", "stuff", "stitching", "embark", "snap", "restricted", "activation", "kit", "collar", "cancel", "seventy", "spin", "lining", "boar", "woolly", "leash", "reviewer", "leather", "note", "aid", "throb", "mutual", "amendment", "adjust", "net", "fix", "rectangle", "avoid", "exclusivity", "functional", "pass"]}
{"label": "bag", "p": 0.04387687146663666, "predictions": ["handbag", "gallantry", "princely", "purse", "bag", "reissue", "tote", "bagful", "waxed", "interrelation", "oriental", "cheery", "suitcase", "physic", "handcraft", "significance", "ethnic", "outwards", "saintly", "imprison", "net", "proverbial", "cheerfully", "brightly", "festive", "sometime", "exhortation", "inhabitant", "bushiness", "solicitation", "transgressor", "considered", "delectably", "beg", "expandable", "debilitated", "deportation", "drawstring", "desirably", "embark", "ceaselessly", "cardiovascular", "baseness", "wheeled", "briefcase", "opening", "washroom", "label", "zip", "hanging", "microeconomics", "dedicate", "cardiac", "indisputable", "constrained", "belongings", "togetherness", "several", "acknowledge", "northwards", "traveling", "climber", "southwestern", "islander", "prevail", "hiatus", "separately", "aspiration", "indicative", "thou", "celibate", "intertwining", "parcel", "dazzling", "ideally", "silkily", "inhumane", "reduced", "materially", "holocaust", "unworldly", "stricken", "backpack", "classically", "separation", "porter", "holidays", "measurable", "handcrafted", "pack", "adventurously", "venomous", "watchfulness", "including", "intermediate", "deceased", "chained", "leather", "retrospectively", "confederacy"]}
{"label": "bag", "p": 0.1381450593471527, "predictions": ["bag", "suitcase", "pack", "prevail", "expandable", "briefcase", "toolkit", "gallantry", "backpack", "pouch", "wheeled", "transpire", "handbag", "backrest", "covert", "reissue", "outwards", "kit", "drawstring", "princely", "built", "amp", "fluster", "porter", "watertight", "beg", "hamper", "conceal", "strap", "belongings", "zip", "valuables", "merchandise", "craftsman", "slightness", "simplex", "purse", "luggage", "tote", "waxed", "survival", "belted", "booster", "baggy", "pocket", "police", "leathery", "external", "durably", "nobleness", "importation", "micro", "reversible", "solicitation", "licensed", "hardily", "concealed", "notebook", "interestedly", "cooler", "radiator", "promotional", "cot", "northwards", "straight", "odyssey", "protector", "responder", "embark", "depend", "poise", "cooling", "folio", "router", "electrify", "trolley", "scarceness", "subdued", "noted", "expertness", "bagful", "repossession", "temptingly", "tux", "wallet", "hex", "drumstick", "nylon", "credential", "quart", "cheery", "administrate", "storehouse", "guarder", "livery", "allocate", "regain", "today", "baggage", "cancel"]}
{"label": "bag", "p": 0.24837031960487366, "predictions": ["bag", "handbag", "princely", "toolkit", "briefcase", "expandable", "pack", "suitcase", "collapsible", "pepper", "drawstring", "tote", "retail", "cot", "label", "bargain", "purse", "registration", "shopping", "waxed", "outwards", "crown", "separation", "impermeable", "ton", "poll", "beg", "repossession", "importation", "alarming", "bagful", "file", "leash", "bellow", "discard", "built", "post", "conceal", "shopper", "reversible", "cheap", "allocate", "regulation", "straight", "weight", "cap", "wagon", "pedigree", "pouch", "inspection", "stoppage", "alert", "mover", "trolley", "note", "opening", "slide", "erect", "protective", "disclaimer", "luggage", "warn", "directly", "lighthouse", "termination", "hardily", "disk", "reparation", "vacuum", "importance", "gallantry", "feed", "confidentiality", "promotional", "clothe", "attention", "depot", "also", "apron", "backrest", "poke", "sticky", "external", "consultation", "transpire", "deluxe", "deal", "mail", "solicitation", "lining", "wheeled", "wheelbarrow", "cancellation", "plenty", "message", "responder", "hark", "subscriber", "resubmit", "gasoline"]}
