{"label": "buzzer", "p": 0.03631352633237839, "predictions": ["induction", "controller", "console", "hub", "buzzer", "momentary", "switch", "hotplate", "control", "platform", "spot", "weight", "disk", "peripheral", "install", "panic", "fixture", "framework", "lid", "paperback", "node", "disseminate", "pager", "ongoing", "microprocessor", "rotated", "reviewer", "sender", "centralize", "epicenter", "hint", "kilobyte", "pad", "kilogram", "burner", "spectroscope", "scour", "input", "combination", "reset", "indicate", "competency", "enclosure", "standby", "disc", "beacon", "execute", "precise", "on", "step", "knob", "pentagon", "known", "block", "mounting", "point", "action", "locate", "partaker", "riverbed", "pioneer", "unlabeled", "sandal", "milligram", "apart", "complete", "scholarly", "foam", "matcher", "encyclopedic", "optimum", "vinyl", "kilo", "component", "layer", "simulation", "default", "watching", "repeater", "wobble", "receiver", "policy", "rolling", "glass", "stopper", "keepsake", "overpressure", "selector", "destructor", "lack", "eyewitness", "eject", "insight", "suggestion", "cause", "whetstone", "audio", "micron", "external", "semiconductor"]}
{"label": "buzzer", "p": 0.00026340814656578004, "predictions": ["cooler", "heater", "calendar", "contents", "radio", "quart", "list", "temp", "approximatively", "input", "checklist", "disposable", "narration", "inactive", "identifier", "pager", "raid", "document", "optimum", "ping", "charge", "wearable", "prevail", "airing", "delete", "echo", "approval", "radiophone", "complete", "button", "cup", "excite", "battery", "message", "provided", "booster", "bidirectional", "audio", "cancel", "stout", "buttons", "convert", "can", "subtraction", "scoring", "thermometer", "loud", "registration", "vent", "modify", "rename", "layer", "measurer", "resubmit", "drizzle", "oblong", "partitioned", "unplugged", "broadcaster", "grip", "file", "serviceable", "prominent", "saver", "amino", "compatible", "paragraph", "control", "default", "disclaimer", "beeper", "token", "bin", "target", "modem", "simplex", "chooser", "handy", "launch", "vouch", "hub", "beeline", "dictate", "availability", "tally", "enrollment", "chirp", "recent", "trouser", "depend", "conversion", "controller", "hatch", "sedimentation", "convenient", "insert", "eligibility", "reader", "measurement", "blogger"]}
{"label": "buzzer", "p": 0.945641279220581, "predictions": ["buzzer", "tweeter", "weight", "dish", "mounting", "pigtail", "timer", "rifling", "adjustable", "slew", "backspin", "externally", "disk", "bomb", "collapsible", "knob", "vinyl", "eyelet", "sigma", "counterweight", "superstitiously", "momentary", "swivel", "hardened", "force", "micrometer", "bellow", "rotating", "stopper", "moderated", "poppy", "spool", "adjuster", "diametrically", "kilogram", "hockey", "lock", "length", "gasket", "rolling", "transmitter", "pulley", "reset", "ignition", "crimp", "scale", "collar", "geared", "lid", "verbatim", "vaporizer", "dolly", "sealing", "puck", "booster", "regulator", "token", "ox", "bending", "focal", "pedal", "robbing", "detect", "roundness", "upright", "covert", "spin", "contention", "functional", "spotted", "measurer", "overpressure", "depose", "petroleum", "piston", "blacksmith", "deterrent", "filter", "string", "object", "valuables", "ban", "bonded", "asymmetrical", "stud", "skateboard", "rubber", "snug", "dualism", "tether", "circular", "cyclic", "resolver", "clip", "control", "receptacle", "headset", "sounding", "throttle", "spot"]}
{"label": "buzzer", "p": 0.011004607193171978, "predictions": ["switch", "hub", "muffle", "adapter", "enclosure", "component", "modem", "inverter", "module", "node", "connector", "buzzer", "transceiver", "gateway", "plug", "battery", "relay", "verbatim", "clip", "switching", "transistor", "stabilizer", "compatible", "repeater", "riverbed", "semiconductor", "default", "mute", "micron", "flux", "hint", "momentary", "output", "pivotal", "sender", "indexing", "preferential", "wholesale", "splitter", "bending", "partaker", "clapper", "convenient", "step", "external", "checkpoint", "peripheral", "cluster", "refill", "myth", "booking", "offload", "distribution", "unifying", "cryptography", "simplex", "transformer", "inductor", "unlettered", "mild", "beam", "equity", "sensor", "ballast", "competency", "resistive", "kilo", "complete", "ingest", "transmitter", "centralized", "vendor", "wireless", "availability", "checkout", "audio", "pedal", "extrusion", "downgrade", "transmit", "console", "technician", "testimonial", "installment", "backup", "interactive", "measurer", "wrongful", "cache", "editorial", "deadlock", "ranking", "lit", "dissolution", "factory", "efficient", "hotplate", "fuse", "finale", "numerator"]}
{"label": "buzzer", "p": 0.027962293475866318, "predictions": ["pigtail", "lid", "hanger", "buzzer", "pulley", "arc", "circumference", "deadlock", "catheter", "fill", "rotating", "checkup", "hoop", "timer", "circle", "curved", "leash", "headset", "ping", "hub", "tambourine", "externally", "switching", "electrode", "hangman", "circled", "aim", "spin", "pendulum", "prognosis", "label", "encircle", "invalid", "clip", "rolling", "tag", "diametrically", "tangent", "string", "dawdling", "price", "reviewer", "sight", "bond", "hooked", "detect", "magnifier", "chastity", "wit", "bicuspid", "jointed", "curve", "accurateness", "oblong", "clockwise", "bangle", "dished", "yin", "tether", "fasting", "round", "buffer", "hanging", "collapsible", "audio", "disparity", "sinker", "nine", "bottom", "exclamation", "force", "pretension", "objective", "semicircular", "defect", "deduction", "contention", "note", "twist", "diameter", "circling", "dummy", "roller", "oxidized", "bring", "wash", "disjoint", "gassiness", "through", "loud", "inheritable", "counterweight", "biz", "omit", "north", "whistle", "bomb", "suspend", "acceleration", "ingest"]}
{"label": "buzzer", "p": 0.05298493802547455, "predictions": ["round", "buzzer", "oval", "dot", "term", "label", "highlight", "japan", "negative", "subtract", "rounded", "spatter", "button", "circle", "spheroid", "predominantly", "credibly", "uncompressed", "characterization", "prevalent", "incompleteness", "curve", "ban", "infectiousness", "sighted", "hemisphere", "critique", "circled", "squared", "minus", "causer", "comma", "circumference", "opacity", "halves", "occur", "neutral", "encircle", "find", "roundish", "segment", "predominance", "oblong", "caseload", "silt", "induction", "durably", "eccentricity", "horizontal", "mandatory", "basic", "magnitude", "disjoint", "thumb", "chat", "unavailable", "petroleum", "glassy", "ping", "nitrate", "swarm", "demography", "hue", "underline", "disseminate", "unintentional", "myopia", "half", "closely", "cap", "palette", "apostrophe", "extract", "request", "improper", "predominant", "subset", "fill", "diametrically", "degeneration", "plate", "etcetera", "catalyze", "spot", "cornea", "volume", "ellipse", "severity", "ongoing", "thermodynamic", "circling", "sample", "equivalent", "activation", "discoverer", "extrusion", "coercion", "length", "fasting", "rapport"]}
