{"label": "flightiness", "p": 0.00013796240091323853, "predictions": ["monarch", "butterfly", "emerge", "herbivorous", "transformation", "invertebrate", "insect", "copulate", "falter", "transform", "gnat", "pollinator", "woodpecker", "caterpillar", "pales", "mimicry", "darts", "viceroy", "moth", "diffused", "amazing", "macroscopic", "bordered", "malaria", "becoming", "bug", "saffron", "entomology", "spotted", "burying", "nature", "silvery", "large", "showy", "flicker", "vanquisher", "swiftness", "nectar", "obligate", "cased", "rare", "invasive", "fluttering", "befitting", "pollination", "monumental", "cultivator", "macro", "powered", "fauna", "herbivore", "heave", "stinger", "underside", "laying", "naturalist", "lowland", "dragonfly", "hover", "larvae", "length", "wasp", "poisonous", "idealize", "prone", "heftily", "liberty", "bootless", "nonreligious", "newness", "invade", "impenetrable", "species", "memorial", "fluidity", "creeping", "ecology", "had", "plantain", "biological", "clownish", "metamorphosis", "searcher", "entangle", "fashioner", "upper", "beneficial", "buckwheat", "grad", "directly", "sense", "collage", "medulla", "proudly", "scarce", "landfill", "meaningfulness", "gently", "mosquito", "inspiring"]}
{"label": "flightiness", "p": 4.958212957717478e-05, "predictions": ["prospectus", "safeguard", "headway", "twister", "catalog", "leaflet", "hoardings", "stride", "reputable", "zestfully", "insure", "payment", "gust", "waterless", "retread", "winnings", "elect", "industriousness", "outdo", "proceeding", "printing", "letterhead", "wellness", "referendum", "exertion", "advantage", "ensure", "qualifier", "costumer", "renewed", "candidacy", "donated", "brochure", "retrospectively", "superstitiously", "skillfully", "definitively", "enhance", "dependable", "readership", "luminosity", "semifinal", "retailing", "unnecessarily", "subscription", "newsletter", "driven", "leasing", "northwards", "longer", "news", "boost", "convenience", "befall", "voting", "unaccountable", "imperatively", "designing", "biostatistics", "verbalize", "economics", "soften", "worked", "commercialize", "advert", "guiltlessly", "annual", "freestyle", "lottery", "upcoming", "avert", "commotion", "unworried", "bargainer", "forecast", "microeconomic", "missing", "frequent", "wonder", "consumption", "discreet", "brisk", "contractual", "profiting", "speedily", "traveling", "athletics", "caucus", "incorporation", "dealt", "credibly", "sped", "during", "fluidity", "outflow", "tryout", "devaluation", "actively", "governmental", "surety"]}
{"label": "flightiness", "p": 4.7774625272722915e-05, "predictions": ["oriental", "atlas", "cause", "supposing", "illusive", "fuss", "imperialism", "absolutism", "guinea", "religiously", "loyalist", "internationalism", "brutally", "tenderfoot", "anthropomorphic", "map", "kingship", "diplomacy", "fool", "direful", "forcible", "geographical", "fatherland", "wrangle", "colonize", "distempered", "nation", "stamp", "expansionism", "cupid", "hazily", "geopolitics", "predicament", "genus", "anatomically", "artistically", "unification", "ordination", "walkabout", "sludgy", "murdering", "spotted", "typically", "giant", "principality", "front", "known", "mainland", "fortunately", "anthropology", "federation", "ivy", "prodigal", "statehood", "imperialist", "freebie", "reversed", "primates", "princely", "eastern", "cornered", "inequality", "nineteenth", "colonialism", "verminous", "territorial", "distance", "including", "eureka", "haphazard", "symbolic", "murder", "assumed", "introspective", "relinquishment", "affront", "shivering", "unclean", "sooner", "ticklish", "imprint", "evolutionary", "geologic", "courtly", "peace", "ignoramus", "innards", "seasonably", "harmless", "credence", "monogamy", "confederation", "domestication", "propensity", "grapevine", "intertwine", "gregarious", "propaganda", "invulnerable", "bordering"]}
{"label": "flightiness", "p": 4.476219601201592e-06, "predictions": ["plotted", "residual", "magnitude", "scatter", "braille", "correlation", "infectiousness", "bode", "motional", "roundness", "numerically", "evenness", "negatively", "convolution", "paired", "constant", "equivalently", "duration", "derive", "markedly", "regularization", "distinctness", "superconductivity", "experimentally", "variability", "linear", "occurrence", "correlate", "sparse", "interpolation", "variance", "divisor", "admittance", "precipitating", "plotting", "acceptability", "stringency", "proportional", "dispensable", "regression", "coefficient", "slew", "expressed", "cumulative", "continued", "uptake", "habituation", "kinetics", "linearly", "narrower", "sporadic", "spatter", "householder", "coexistent", "unrepeated", "expectancy", "graphically", "preceding", "arithmetically", "denote", "weakening", "chemically", "gestation", "resulting", "curtailment", "proliferation", "systematically", "triglyceride", "regress", "approximation", "exponential", "increasingly", "likelihood", "intensity", "incidence", "magnetization", "syllabic", "propensity", "statistically", "retrace", "deviation", "undamaged", "coincident", "weighted", "inverse", "selectivity", "anarchistic", "intelligibility", "multiplier", "weighting", "eccentricity", "prevalence", "inversely", "unstained", "vertically", "physiologic", "demagnetization", "binomial", "specificity", "lowermost"]}
{"label": "flightiness", "p": 3.163152723573148e-05, "predictions": ["vestibule", "centrally", "troublesome", "reputedly", "mortuary", "burglarproof", "hanging", "watertight", "annex", "toiled", "denominate", "slightness", "degenerate", "entangle", "fourthly", "entrance", "fleshly", "adjoining", "guillotine", "rudimentary", "buckwheat", "bygone", "correctional", "daringness", "walkout", "expedient", "anarchistic", "deadlock", "upper", "affable", "gallows", "vileness", "outermost", "herein", "confession", "deterioration", "abridge", "typically", "farmhand", "arched", "counteraction", "crematorium", "shining", "forcible", "forgery", "leaded", "gastronomical", "copulate", "apparition", "markedly", "speculator", "enclose", "halfway", "threefold", "thereafter", "widen", "graven", "apothecary", "scoff", "intangibility", "floppily", "repulsion", "spite", "pulverize", "gladly", "predicament", "decadency", "columbine", "freehold", "northwards", "quartered", "weakly", "companionable", "backstairs", "revolving", "entering", "incestuous", "invariability", "segregate", "piss", "slaveholder", "insulated", "observer", "smut", "convenient", "duplex", "reformatory", "unenlightened", "distempered", "uncultivated", "famously", "indecipherable", "eminent", "sundry", "externally", "veritable", "fidelity", "grew", "vandalism", "bargainer"]}
