{"label": "lemon", "p": 0.004776892717927694, "predictions": ["sour", "lime", "sunshine", "halves", "citrus", "inlay", "tartness", "zest", "lemon", "citric", "lemonade", "garnish", "anus", "holy", "peel", "acidic", "peace", "sun", "squeeze", "mandarin", "breadfruit", "wholeness", "carefree", "fuss", "various", "brighten", "yellow", "peeled", "orange", "half", "sunshiny", "curd", "halved", "whole", "modify", "roving", "circularity", "navigate", "honeydew", "fleshy", "segment", "kiwi", "seasonably", "rising", "slice", "chips", "boiled", "monogram", "ideal", "condom", "faction", "arose", "orgasm", "roundworm", "halve", "reload", "sample", "purity", "seem", "shaped", "religious", "disposable", "acidity", "object", "genetically", "rupee", "saline", "fidelity", "radial", "wax", "beaming", "dauntless", "shine", "green", "implantation", "leavings", "scant", "sense", "limes", "prawn", "candied", "through", "joy", "tutu", "sclerosis", "punch", "chemotherapy", "dandelion", "essential", "scrub", "cup", "shot", "sight", "partly", "valued", "shrimp", "prosperity", "tricolor", "asexually", "paring"]}
{"label": "lemon", "p": 0.0369015708565712, "predictions": ["sour", "lime", "acidic", "halves", "orange", "lemon", "citric", "citrus", "mandarin", "squeeze", "limes", "peel", "zest", "equivalent", "halved", "segment", "green", "tartness", "acidity", "half", "essential", "lemonade", "lettuce", "paring", "sunshine", "whole", "pork", "mudguard", "pacifism", "faction", "freshness", "drink", "scrub", "sliced", "slice", "fidelity", "peace", "grapefruit", "juice", "tang", "halve", "insufficiently", "object", "ecologic", "religious", "lengthwise", "seem", "ruby", "coinage", "breadfruit", "sun", "yellow", "unlike", "permission", "size", "circularity", "condom", "secularism", "carefree", "leavings", "navigate", "compare", "hateful", "fresh", "candied", "fraction", "activity", "sclerosis", "knock", "manlike", "republicanism", "rind", "clincher", "purposefully", "ideal", "salmon", "garnish", "turnover", "lifestyle", "reminder", "tomorrow", "cleanse", "various", "meal", "bicyclist", "stale", "negativity", "radius", "pair", "orientation", "cyanide", "hint", "bitter", "noun", "seasonably", "diversify", "mimosa", "fleshy", "scrutinize", "shot"]}
{"label": "lemon", "p": 5.7836183259496465e-05, "predictions": ["blob", "ditto", "point", "spot", "ducky", "bring", "silence", "drippy", "peasant", "afraid", "sad", "acceptable", "rhyme", "responder", "fishy", "cap", "clap", "coercion", "beeline", "compatible", "rapport", "oppose", "tater", "hold", "inflated", "bloated", "message", "rotating", "hungry", "slime", "pie", "icon", "feel", "itch", "evaporate", "sticker", "happy", "tattle", "coupon", "punch", "dot", "seem", "danger", "scatter", "canary", "parentheses", "hunger", "tough", "twist", "footstep", "verbalize", "thumb", "sample", "construct", "fancy", "chirp", "snap", "comma", "minus", "plenty", "generate", "muffin", "urine", "negative", "mutual", "even", "spoilage", "oxygen", "cheese", "adopt", "recur", "sole", "tag", "have", "courteous", "vowel", "pear", "character", "unlabeled", "temperament", "vignette", "pepper", "unhappy", "neutral", "label", "cheesy", "threesome", "explain", "selfish", "cytoplasm", "quit", "these", "protection", "indifferent", "subtraction", "squashy", "plank", "attitude", "severity", "you"]}
{"label": "lemon", "p": 0.09891818463802338, "predictions": ["sour", "peel", "lemon", "lime", "rind", "orange", "squeeze", "apricot", "egg", "peeled", "compare", "acidic", "zest", "puff", "peach", "spot", "syrupy", "cantaloupe", "mango", "whole", "pear", "lemonade", "grapefruit", "genetically", "seem", "sponge", "conception", "halves", "size", "stale", "citric", "bumpy", "lipstick", "squash", "condom", "punch", "tang", "fireball", "ovum", "drink", "halved", "peer", "fresh", "canary", "mandarin", "mimosa", "carrot", "pin", "bun", "sun", "yellow", "poppy", "pair", "fortune", "cheese", "segment", "cap", "point", "label", "ball", "exaggerated", "salmon", "citrus", "tartness", "comparable", "roll", "taste", "core", "cashew", "bloated", "mustard", "half", "swelling", "ducky", "acidity", "crisp", "tangerine", "sad", "foot", "diversify", "urine", "melt", "disposable", "smear", "footstep", "combination", "spoilage", "blend", "hint", "butter", "paw", "twist", "inedible", "beehive", "ideal", "bread", "halve", "fuss", "far", "vouch"]}
{"label": "lemon", "p": 0.00034373148810118437, "predictions": ["sour", "fortune", "peel", "acidic", "materialize", "modify", "condom", "beeswax", "hint", "halves", "clap", "cantaloupe", "own", "squeeze", "slice", "size", "ouch", "faction", "carefree", "rind", "lemonade", "butter", "peace", "halved", "punch", "sliced", "anemia", "orange", "mimosa", "egg", "essential", "prefer", "refusal", "honeydew", "drink", "or", "scrub", "sunshine", "watermelon", "mango", "green", "lime", "zest", "dullness", "more", "half", "ideal", "valid", "suppository", "taste", "compare", "peeled", "absorb", "segment", "sponge", "detox", "equivalent", "backward", "mild", "rank", "fidelity", "sample", "cleanse", "tuberculosis", "no", "disposable", "soy", "related", "twist", "dietary", "boon", "freshness", "streak", "reminder", "uninterrupted", "through", "foundation", "scrape", "comparable", "distinguish", "remove", "heal", "wax", "activity", "lipstick", "rub", "compatible", "aroma", "nectar", "urgent", "yellow", "tartness", "complete", "distinctive", "diet", "cheese", "flip", "lengthwise", "opera", "scurvy"]}
{"label": "lemon", "p": 0.008840823546051979, "predictions": ["lime", "sour", "limes", "lemon", "citric", "citrus", "halves", "acidic", "halve", "lemonade", "seem", "tartness", "orange", "disposable", "kiwi", "opaque", "soy", "green", "halved", "olive", "compare", "fruitful", "squeeze", "guava", "pair", "peeled", "size", "honeydew", "diversify", "fresh", "rind", "ecological", "peel", "margarita", "pear", "diversified", "paring", "pea", "whole", "detoxification", "nourishment", "apricot", "shamrock", "cranberry", "coconut", "separate", "half", "fidelity", "mango", "unseasonable", "lengthwise", "distinguish", "varying", "yellow", "prefer", "algae", "entangle", "ecologic", "gradually", "circumcised", "fractional", "acrid", "cider", "luck", "unripe", "comparable", "soluble", "budding", "prospect", "rank", "misfortune", "freshness", "hint", "vouch", "complete", "partially", "sunshine", "zest", "various", "equivalent", "sliced", "heredity", "circularity", "cleanse", "suppress", "buttercup", "brown", "curd", "differentiation", "uninterrupted", "bunch", "methodical", "fleshy", "dullness", "stale", "balm", "rotated", "syrupy", "positioning", "these"]}
{"label": "lemon", "p": 0.47303831577301025, "predictions": ["lemon", "lime", "zest", "mango", "ecological", "leaf", "sour", "fresh", "yellowing", "vouch", "pear", "orange", "ginger", "carrot", "tartness", "olive", "cantaloupe", "leave", "egg", "hop", "butter", "sweeper", "photosynthesis", "spindle", "mustard", "soap", "breadfruit", "undulated", "ham", "halve", "paring", "persistent", "ducky", "apricot", "cheese", "ecologic", "greener", "rotated", "laurel", "mimosa", "syrupy", "guava", "cerebellum", "balm", "unseasonable", "activation", "lemonade", "overlapping", "kelp", "hamburger", "viable", "bomb", "seem", "rind", "yellow", "seedling", "squeeze", "boon", "gradually", "rocket", "bouncing", "launch", "federate", "far", "citrus", "nectar", "length", "robust", "acidic", "coconut", "sunshine", "master", "punch", "sprout", "spot", "genetically", "carrying", "fruitful", "photosynthetic", "beehive", "yellowish", "optimistic", "boar", "slow", "inflexible", "citric", "bowls", "buttercup", "livelihood", "bun", "pair", "insignificant", "floater", "insecticide", "collapsible", "separating", "waterless", "rotation", "peeled", "soften"]}
{"label": "lemon", "p": 0.2349187731742859, "predictions": ["lime", "lemon", "sour", "zest", "orange", "punch", "peel", "rind", "acidic", "compare", "boar", "squeeze", "fresh", "whole", "seem", "syrupy", "spot", "peeled", "egg", "halve", "bumpy", "monk", "accomplish", "citric", "mango", "mandarin", "carrot", "robin", "mustard", "apricot", "vouch", "floater", "upstairs", "federate", "sunshine", "far", "point", "paring", "gripping", "personage", "japan", "salmon", "unlike", "prospect", "sclerosis", "pancake", "citrus", "stale", "warty", "tangerine", "rotated", "drink", "negativity", "inflation", "derive", "puff", "fleshy", "sad", "ducky", "yellow", "half", "gradually", "undulated", "individuality", "cap", "distinguish", "pear", "comparable", "hold", "fortune", "size", "cataract", "insufficiently", "red", "alarming", "treating", "cardinal", "activation", "conception", "genetically", "cantaloupe", "spoilage", "unseasonable", "transporting", "cyanide", "clap", "tartness", "neutral", "varying", "conclusion", "bouncing", "appreciable", "trolley", "fist", "butter", "gestation", "ovum", "inventive", "uncompressed", "economize"]}
