{"label": "program", "p": 1.0406166438770015e-05, "predictions": ["interdisciplinary", "supervision", "cooperate", "connection", "mediator", "participate", "implementation", "collaborative", "consolidate", "integration", "methodology", "teamwork", "discussion", "solution", "skill", "join", "facilitation", "consult", "joining", "connect", "resource", "interpersonal", "integrate", "behavioral", "supplier", "dispute", "consultative", "compatibility", "dialogue", "reciprocity", "project", "group", "inquiry", "regional", "centralize", "consultation", "participation", "puzzle", "rapport", "cognitive", "conclusion", "establish", "organization", "agreement", "contribute", "interaction", "service", "capability", "communication", "referral", "psychological", "standardize", "suitability", "language", "harmonization", "collaboration", "tutor", "arbitration", "approach", "advocacy", "web", "inhibitor", "inclusive", "bargaining", "persuade", "cognition", "team", "matching", "mentor", "translation", "exchange", "configuration", "disseminate", "introduction", "screening", "unified", "cultural", "autism", "facilitate", "cooperation", "consolidation", "accusation", "affiliation", "reputation", "restructuring", "understand", "committee", "ensemble", "sociological", "finished", "provider", "meeting", "client", "supply", "culture", "negotiation", "sped", "enzyme", "disagreement", "transferable"]}
{"label": "program", "p": 6.0718935856129974e-05, "predictions": ["conversation", "connection", "talking", "discuss", "discussion", "cohesion", "speaking", "dialogue", "semantic", "opinion", "scoring", "chemistry", "communicating", "group", "talk", "deadlock", "socialize", "argumentation", "hierarchy", "node", "interpret", "interpersonal", "centralize", "communication", "socialization", "parenting", "catalyze", "onto", "network", "collaborative", "engage", "presentation", "join", "hobby", "bilingual", "cyanide", "artist", "involve", "language", "science", "polymer", "mediator", "chirp", "recurrent", "cooperative", "breadth", "conversational", "sociable", "bases", "think", "sampling", "bring", "speak", "learner", "equality", "interaction", "kitty", "synthesize", "debate", "insight", "bouncing", "influencer", "kinship", "parent", "peer", "variable", "inquiry", "viable", "relatedness", "hierarchical", "livelihood", "inequality", "connect", "molecule", "say", "contribute", "interdisciplinary", "relation", "congruently", "adhesion", "participation", "structure", "genetic", "connectivity", "weak", "networking", "debating", "dependency", "passive", "stimuli", "centralization", "cloning", "traversal", "consultation", "referral", "collectivism", "inorganic", "understand", "facilitator", "photochemistry"]}
{"label": "program", "p": 9.9843782663811e-06, "predictions": ["emotionally", "psychotherapy", "decidedly", "intimate", "absurdity", "together", "poignant", "couple", "conversation", "grew", "addict", "camaraderie", "sixties", "sensitiveness", "marriage", "alcoholic", "whispering", "therapy", "immaturely", "muse", "rebuke", "alone", "therapist", "placebo", "delinquent", "mourn", "chasing", "erotic", "impression", "disembodied", "wrongful", "dating", "courteousness", "interestedly", "disoriented", "acquainted", "parenting", "infidelity", "longing", "regimentation", "dejected", "feel", "psychoanalytic", "giver", "impatience", "momentous", "touchy", "leaving", "spank", "reciprocation", "meticulous", "scriptwriter", "compassion", "embracing", "maternity", "incestuous", "contradict", "stringently", "fuss", "mediate", "empathy", "hug", "pace", "conversational", "sundry", "forties", "scold", "admirable", "incorporation", "stumble", "gentle", "rapport", "soak", "acknowledge", "butch", "padre", "hold", "tattooing", "disclosure", "mediating", "regretful", "lesbian", "exertion", "smut", "boyhood", "passionately", "patiently", "famously", "rivalry", "lover", "inexperience", "obscene", "negotiate", "likely", "caught", "bridegroom", "shabbily", "indifference", "inducement", "companionship"]}
{"label": "program", "p": 2.7012920327251777e-05, "predictions": ["heading", "semantically", "comparable", "bibliographic", "abbreviated", "registrant", "stringency", "subsection", "snippet", "retraction", "excerpt", "regularization", "indent", "default", "breakpoint", "indentation", "infectiousness", "itinerary", "resume", "citied", "materiality", "precipitating", "annotation", "outline", "issuer", "reviewer", "syllabic", "chronology", "paired", "particulars", "markup", "thermodynamic", "representativeness", "demerit", "compiler", "annotate", "budgetary", "attributable", "chronologically", "footnote", "incompleteness", "primer", "expressed", "identifier", "signification", "derivation", "memo", "conjunctive", "chemically", "causing", "deletion", "quantitatively", "citation", "converting", "profile", "whereas", "substantive", "readjustment", "problematic", "causative", "moderated", "federate", "morbidity", "incrementally", "biophysical", "correlate", "emotionality", "complicatedness", "undetermined", "stipend", "recipient", "narrower", "statement", "optically", "bibliography", "indicative", "implicitly", "substituted", "severity", "occurrence", "implicit", "attainment", "varying", "accommodative", "readability", "traversal", "increasingly", "injunction", "basic", "recoverable", "motional", "title", "minimization", "roundness", "psychoses", "verbose", "schizophrenia", "laterally", "dynamically", "regressive"]}
{"label": "program", "p": 0.00022490060655400157, "predictions": ["transform", "with", "giveaway", "headway", "maximum", "awesome", "whose", "poll", "finalist", "trivia", "involved", "aware", "critically", "unite", "that", "get", "are", "private", "now", "appreciate", "normal", "parental", "slay", "mainly", "sat", "everyone", "thumbnail", "friendly", "practice", "of", "thanks", "platonic", "talent", "bother", "awareness", "peer", "sooner", "welfare", "euthanasia", "crafty", "nation", "temporary", "available", "twentieth", "unpaid", "introverted", "bargain", "unacceptable", "winner", "confidence", "nationwide", "mayo", "feminist", "inflation", "myself", "made", "intent", "clearance", "morals", "break", "for", "making", "win", "happen", "differentiation", "rearrange", "uncommon", "whole", "neutral", "daring", "later", "vacancy", "immediately", "seize", "their", "thank", "there", "worthwhile", "attention", "derogatory", "really", "your", "would", "never", "dividend", "prevent", "foreskin", "jerk", "new", "so", "bring", "activate", "evacuate", "mean", "eliminate", "repeatedly", "motivate", "immorality", "academy", "charity"]}
{"label": "program", "p": 0.00027414492797106504, "predictions": ["multimedia", "social", "translator", "blog", "tic", "media", "distribution", "learning", "licensing", "lottery", "establish", "bingo", "marketing", "messaging", "printing", "sat", "multilingual", "contact", "directory", "messenger", "sport", "join", "affiliate", "expense", "inbound", "hobby", "icon", "synergy", "domain", "asset", "mobility", "startup", "feedback", "analysis", "importation", "credit", "stem", "python", "publish", "accounting", "process", "promotion", "consolidate", "promotional", "reliable", "automated", "course", "exchange", "site", "assets", "digital", "recommendation", "translation", "commercialize", "combination", "interactive", "dialogue", "print", "group", "chatting", "digitization", "days", "commonly", "contextual", "budget", "policy", "reputation", "freelance", "support", "expenses", "designed", "project", "trademark", "installment", "methodology", "pivotal", "franchise", "instruction", "enrichment", "language", "restore", "scoring", "knowhow", "product", "secure", "digits", "accessible", "valuation", "deployment", "job", "multinational", "localization", "earning", "advantage", "supply", "recycling", "exceeding", "influencer", "facilities", "grammar"]}
