{"label": "solidness", "p": 1.4582164112653118e-05, "predictions": ["equator", "atlas", "numerously", "easternmost", "geologic", "seismically", "definitively", "inaccessibility", "modernistic", "expansive", "rudimentary", "overflow", "immaterial", "freehold", "slightness", "typically", "antiquity", "vandalism", "disrepair", "geographically", "undamaged", "tether", "speculator", "reciprocally", "emphases", "wetness", "highest", "retaining", "honorableness", "outgrowth", "nineteenth", "desecration", "seacoast", "regionalism", "southwestern", "turquoise", "chillness", "temporally", "unworried", "fourthly", "seismological", "irregularly", "historiographer", "meteorological", "seismology", "damsel", "outskirt", "columbine", "superstitiously", "adventurously", "pleasant", "unassuming", "clamminess", "unshakable", "specifics", "northeasterly", "glowingly", "durably", "withstood", "subtropics", "tropic", "geological", "characteristically", "compacted", "splitting", "amidst", "mare", "presidential", "habitant", "variously", "fastness", "encroachment", "airspace", "creeper", "hollowly", "elsewhere", "inelegantly", "storied", "amicability", "subjection", "sublimely", "reunite", "lofty", "horizontal", "unspecified", "chilliness", "vague", "arduously", "aplenty", "invariability", "mammary", "indecipherable", "harmoniousness", "overflowing", "intrusion", "roughly", "heftily", "dump", "communistic", "symbolization"]}
{"label": "solidness", "p": 2.5598965294193476e-06, "predictions": ["scratchy", "stitch", "mangle", "panicked", "bashful", "itchy", "companion", "shamrock", "wander", "tom", "bases", "ashamed", "batty", "moo", "cartoon", "bother", "reviewer", "hyper", "gladly", "gloom", "between", "scientifically", "lucky", "kitty", "mighty", "tux", "insulting", "messaging", "favor", "angrily", "character", "read", "scout", "hi", "medley", "buyer", "establish", "peer", "transformation", "science", "teaching", "wildcat", "lamb", "employ", "tweak", "contribute", "snuggle", "badness", "oilman", "pal", "carry", "clover", "frosty", "villainous", "snoring", "scratch", "ditto", "objection", "team", "noteworthy", "engaging", "neuter", "collaborative", "disagree", "conscience", "regular", "exceed", "humming", "scientist", "crime", "bankrupt", "screwy", "mediate", "personally", "devious", "collaboration", "mingle", "trivia", "have", "dissatisfaction", "morale", "moderator", "grumble", "hug", "grammar", "springing", "centered", "smashing", "join", "lovingly", "piglet", "compassionate", "adopt", "twinkle", "multiply", "approachable", "ecology", "peacemaking", "hibernate", "tickle"]}
{"label": "solidness", "p": 0.026924701407551765, "predictions": ["solidness", "rename", "parentheses", "fist", "unmannered", "thieving", "and", "assertion", "northwards", "reply", "agitate", "convert", "swiftness", "bitmap", "companion", "gunpowder", "ambiguity", "disposal", "backward", "postscript", "consequent", "solo", "forefinger", "tranquilly", "cursor", "headstrong", "parenthesis", "contrast", "intangibility", "possessor", "administrate", "finish", "contrarily", "inflict", "undisciplined", "did", "debatable", "hobble", "dissemble", "incisiveness", "asymmetric", "captivation", "forcefulness", "bondman", "disparage", "ringing", "reciprocation", "numerable", "unlearned", "harass", "troublesome", "accusation", "honorableness", "approximatively", "theatricals", "duskiness", "reviewer", "afflict", "overstep", "robbing", "hyphen", "assured", "infidel", "ambiguous", "squared", "anecdote", "sickle", "fancy", "hostility", "obtrusive", "unenlightened", "modify", "supporter", "wordy", "apprehend", "unluckily", "vileness", "disappearing", "unknown", "verbalize", "forwards", "barking", "repeat", "rip", "loath", "opponent", "inflection", "configure", "preview", "athletic", "cosmetology", "lookup", "credence", "enforcement", "transpire", "antagonism", "approximately", "clockwise", "phone", "unattached"]}
{"label": "solidness", "p": 8.398731665693049e-07, "predictions": ["alleviate", "wring", "rinse", "vaccine", "airway", "through", "aesthetic", "therapeutic", "ouch", "inject", "hygiene", "hypertension", "euthanasia", "elbow", "dislocation", "injection", "penetrating", "ticklish", "rid", "activator", "vaccination", "rubbing", "grip", "punish", "checkup", "fornication", "technically", "grasp", "administer", "unconscious", "gout", "neck", "sore", "sexual", "examine", "aspirate", "tetanus", "handover", "aching", "stimulate", "cramp", "sex", "protecting", "marry", "forearm", "chiropractic", "padre", "pleasurable", "estrogen", "establish", "compatible", "mouthpiece", "gestational", "dexterous", "painful", "dysfunction", "sinful", "biopsy", "cosmetology", "teat", "acupuncture", "empower", "dominant", "stink", "pinched", "functional", "unplug", "prick", "addict", "lovingly", "arms", "wash", "tourniquet", "foreskin", "scabby", "fill", "sedative", "accusation", "domineering", "burn", "rapport", "stimulating", "demanding", "prognosis", "refusal", "immunization", "fondness", "diabetes", "thyroid", "clammy", "questionable", "flipper", "erectness", "steroids", "inserted", "inability", "examination", "withdrawal", "snatched", "pinch"]}
{"label": "solidness", "p": 3.4600705021148315e-06, "predictions": ["dysfunction", "surrogate", "flabby", "contusion", "pregnancy", "shoulder", "precocious", "erogenous", "auditory", "zoned", "edema", "frigidity", "deficiency", "hormonal", "chubby", "insufficiency", "pheromone", "induce", "properly", "impotence", "uncontrolled", "exhalation", "pornography", "reawakening", "migraine", "traumatic", "exertion", "supposed", "articulation", "obstructive", "involuntary", "underarm", "explanation", "profile", "estrogen", "spasm", "meningitis", "regressive", "tetanus", "receptive", "sensitive", "piles", "acknowledge", "dehydration", "refusal", "orgasm", "maltreatment", "prolonged", "plump", "breastfeeding", "rapport", "mindset", "unassisted", "acidity", "impregnate", "shrinkage", "tightness", "overweight", "seizure", "gastrointestinal", "critically", "appropriate", "sclerosis", "fascinating", "headfirst", "discordance", "lupus", "congenital", "adulterer", "elicit", "poisoning", "unborn", "menstrual", "rid", "induced", "soothe", "therapeutic", "fleshy", "infinitive", "defensiveness", "mental", "conceive", "symptom", "replenish", "masturbation", "itch", "rigidity", "foreskin", "tapping", "autoimmune", "uncultured", "pinched", "lactation", "posture", "erect", "lymph", "tract", "characteristics", "healthiness", "wakefulness"]}
{"label": "solidness", "p": 0.05426708608865738, "predictions": ["cap", "fitted", "solidness", "slew", "snug", "collar", "spotted", "dice", "brake", "dummy", "film", "observer", "retrograde", "geared", "hatch", "duskiness", "distinct", "domino", "mounting", "ringing", "peaked", "known", "midshipman", "mystery", "durably", "visor", "backrest", "rip", "tether", "hinge", "phases", "erectly", "carriageway", "fancy", "reel", "girth", "random", "decal", "traps", "accolade", "northwards", "emit", "evaporate", "micron", "booster", "cyclic", "courteous", "ingest", "phase", "ghostly", "rational", "mudguard", "sniff", "covert", "dignitary", "apostrophe", "telephone", "dispensable", "gasket", "macroscopic", "sad", "shady", "hub", "cause", "biz", "coloring", "precipitation", "gag", "scoff", "diffusion", "powered", "palatable", "equivalently", "footstep", "poorly", "progeny", "pedal", "protective", "peace", "perpetrate", "bored", "plenty", "clamp", "kingship", "grumble", "take", "seek", "verbatim", "kilogram", "durable", "anarchistic", "controller", "conditioned", "helm", "male", "transpose", "reciprocation", "abortive", "basic", "ingenuity"]}
{"label": "solidness", "p": 2.911647970904596e-05, "predictions": ["parted", "encryption", "microeconomics", "programming", "microeconomic", "regionalism", "rationalistic", "incompleteness", "decryption", "accustomed", "delirium", "demonstrable", "watchfulness", "discern", "compile", "whatsoever", "signification", "reciprocation", "pseudoscience", "heightened", "attribute", "functionalism", "proverbial", "compositional", "whereas", "depopulation", "tribulation", "schizophrenic", "industriousness", "numerical", "incorrectly", "coding", "reviewer", "paradoxically", "metaphysic", "neurotransmitter", "wordlessly", "fitful", "rework", "manifesto", "empirical", "biostatistics", "encode", "psychosis", "defined", "propositional", "lisp", "numerable", "kernel", "cryptography", "wakefulness", "agnosticism", "emulation", "mentally", "humanistic", "farther", "archetypal", "psychopathology", "unchanging", "retrieval", "regularity", "sedative", "exhortation", "preamble", "discernment", "textual", "retributive", "phraseology", "slothful", "theism", "collectivism", "readjustment", "mentality", "ceaselessly", "motional", "positivism", "religiousness", "tangibly", "sclerosis", "glorification", "causative", "compiler", "accusative", "loath", "folktale", "conjuncture", "virtuous", "corporeal", "fleshly", "condemnation", "timeliness", "federation", "geopolitical", "heartlessness", "borderline", "fallacious", "denominate", "episcopal", "stock", "descriptive"]}
{"label": "solidness", "p": 1.7497269482191768e-06, "predictions": ["coincident", "curtailment", "infectiousness", "waviness", "incompleteness", "deflection", "elasticity", "demagnetization", "bracing", "refractive", "interpolation", "quota", "regularization", "discharging", "negatively", "householder", "expansionary", "graphically", "paired", "motional", "proportionality", "easement", "extent", "maximization", "statics", "beam", "proliferation", "impedance", "inclination", "propensity", "stringency", "vaporization", "arithmetically", "overpressure", "proportional", "perpendicularly", "intonation", "proximal", "intercept", "instantaneous", "regressive", "regress", "admittance", "trigonometry", "postulate", "coefficient", "constant", "incidence", "inversely", "roughness", "stiffness", "induced", "refraction", "displacement", "varying", "habituation", "markedly", "flatness", "magnification", "disparity", "uptake", "proofs", "derivative", "kinetics", "regression", "temporally", "numerically", "friction", "residual", "roundness", "oscillator", "resistive", "retrace", "hardening", "trigonometric", "instability", "laterally", "spectroscope", "superconductivity", "sustained", "magnetization", "incision", "duration", "forwards", "deceleration", "illegitimacy", "characteristic", "quantitatively", "permeability", "normally", "equivalently", "narrower", "latency", "predominance", "slope", "perpetuity", "linearly", "analogue", "tensile", "allowable"]}
